wikibee/__init__.py
wikibee/__main__.py
wikibee/cli.py
wikibee/client.py
wikibee/formatting.py
wikibee/tts_normalizer.py
wikibee/tts_openai.py
wikibee-0.1.0.dist-info/METADATA
wikibee-0.1.0.dist-info/WHEEL
wikibee-0.1.0.dist-info/entry_points.txt
wikibee-0.1.0.dist-info/licenses/LICENSE
wikibee-0.1.0.dist-info/RECORD
