Metadata-Version: 2.4
Name: wikibee
Version: 0.1.0
Summary: Extract Wikipedia articles and convert them to TTS-friendly text and audio
Project-URL: Homepage, https://github.com/patrickdeanbrown/wikibee
Project-URL: Repository, https://github.com/patrickdeanbrown/wikibee
Project-URL: Issues, https://github.com/patrickdeanbrown/wikibee/issues
Author-email: Patrick Brown <patrickdeanbrown@icloud.com>
License: MIT
License-File: LICENSE
Keywords: audio,extraction,text-to-speech,tts,wikipedia
Classifier: Development Status :: 4 - Beta
Classifier: Environment :: Console
Classifier: Intended Audience :: End Users/Desktop
Classifier: License :: OSI Approved :: MIT License
Classifier: Operating System :: OS Independent
Classifier: Programming Language :: Python :: 3
Classifier: Programming Language :: Python :: 3 :: Only
Classifier: Programming Language :: Python :: 3.8
Classifier: Programming Language :: Python :: 3.9
Classifier: Programming Language :: Python :: 3.10
Classifier: Programming Language :: Python :: 3.11
Classifier: Programming Language :: Python :: 3.12
Classifier: Programming Language :: Python :: 3.13
Classifier: Topic :: Internet :: WWW/HTTP :: Browsers
Classifier: Topic :: Multimedia :: Sound/Audio :: Speech
Classifier: Topic :: Text Processing :: Markup
Classifier: Topic :: Utilities
Requires-Python: >=3.8
Requires-Dist: inflect>=6.0
Requires-Dist: num2words>=0.5.0
Requires-Dist: openai>=1.0.0
Requires-Dist: requests>=2.0
Requires-Dist: rich>=13.0
Requires-Dist: typer>=0.12
Provides-Extra: dev
Requires-Dist: pre-commit>=3.5.0; extra == 'dev'
Requires-Dist: pytest>=6.0; extra == 'dev'
Requires-Dist: requests-mock>=1.11.0; extra == 'dev'
Requires-Dist: ruff>=0.0.0; extra == 'dev'
